LICENSE
README.md
setup.py
serial_id.egg-info/PKG-INFO
serial_id.egg-info/SOURCES.txt
serial_id.egg-info/dependency_links.txt
serial_id.egg-info/not-zip-safe
serial_id.egg-info/top_level.txt
serialid/__init__.py
serialid/api.py
serialid/base32.py
serialid/codec.py
serialid/consts.py
serialid/hints.py
serialid/providers.py
serialid/py.typed
serialid/serialid.py
serialid/time.py