Metadata-Version: 2.1
Name: serial-id
Version: 0.1
Summary: Sequential Unique Short & Sortable Identifier
Home-page: https://github.com/mysteryjeans/serial-id
Author: Faraz Khan
Author-email: mk.faraz@gmail.com
License: MIT License
Classifier: Development Status :: 5 - Production/Stable
Classifier: Intended Audience :: Developers
Classifier: Natural Language :: English
Classifier: License :: OSI Approved :: MIT License
Classifier: Programming Language :: Python
Classifier: Programming Language :: Python :: 3
Classifier: Programming Language :: Python :: 3.5
Classifier: Programming Language :: Python :: 3.6
Classifier: Programming Language :: Python :: 3.7
Classifier: Programming Language :: Python :: 3.8
Classifier: Topic :: Software Development :: Libraries :: Python Modules
License-File: LICENSE
